mapping_suite_sdk/__init__.py
mapping_suite_sdk/adapters/__init__.py
mapping_suite_sdk/adapters/extractor.py
mapping_suite_sdk/adapters/hasher.py
mapping_suite_sdk/adapters/loader.py
mapping_suite_sdk/adapters/repository.py
mapping_suite_sdk/adapters/serialiser.py
mapping_suite_sdk/adapters/tracer.py
mapping_suite_sdk/adapters/validator.py
mapping_suite_sdk/entrypoints/__init__.py
mapping_suite_sdk/entrypoints/cli/__init__.py
mapping_suite_sdk/entrypoints/cli/mssdk.py
mapping_suite_sdk/entrypoints/cli/validate.py
mapping_suite_sdk/models/__init__.py
mapping_suite_sdk/models/asset.py
mapping_suite_sdk/models/core.py
mapping_suite_sdk/models/mapping_package.py
mapping_suite_sdk/services/__init__.py
mapping_suite_sdk/services/load_mapping_package.py
mapping_suite_sdk/services/serialise_mapping_package.py
mapping_suite_sdk/services/validate_mapping_package.py
mapping_suite_sdk/utils.py
mapping_suite_sdk/vars.py
mapping_suite_sdk-0.3.0.dist-info/LICENSE
mapping_suite_sdk-0.3.0.dist-info/METADATA
mapping_suite_sdk-0.3.0.dist-info/WHEEL
mapping_suite_sdk-0.3.0.dist-info/entry_points.txt
mapping_suite_sdk-0.3.0.dist-info/RECORD
