Metadata-Version: 2.3
Name: mapping-suite-sdk
Version: 0.3.0
Summary: Software development kit for XML-RML mapping rules packaging
Author: meaningfy.ws
Author-email: hi@meaningfy.ws
Requires-Python: >=3.12
Classifier: Programming Language :: Python :: 3
Classifier: Programming Language :: Python :: 3.12
Classifier: Programming Language :: Python :: 3.13
Requires-Dist: gitpython (>=3.1.44,<4.0.0)
Requires-Dist: lxml (>=5.3.1,<6.0.0)
Requires-Dist: openpyxl (>=3.1.5,<4.0.0)
Requires-Dist: opentelemetry-api (>=1.30.0,<2.0.0)
Requires-Dist: opentelemetry-instrumentation (>=0.51b0,<0.52)
Requires-Dist: opentelemetry-sdk (>=1.30.0,<2.0.0)
Requires-Dist: pandas (>=2.2.3,<3.0.0)
Requires-Dist: pydantic (>=2.10.6,<3.0.0)
Requires-Dist: pymongo (>=4.11.1,<5.0.0)
Requires-Dist: typer (>=0.15.3,<0.16.0)
